zen_auth/__init__.py
zen_auth/_version.py
zen_auth/claims/__init__.py
zen_auth/claims/base.py
zen_auth/config/__init__.py
zen_auth/config/config.py
zen_auth/dto/__init__.py
zen_auth/dto/claims.py
zen_auth/dto/role.py
zen_auth/dto/scope.py
zen_auth/dto/user.py
zen_auth/errors/__init__.py
zen_auth/errors/claims.py
zen_auth/errors/config.py
zen_auth/errors/rbac.py
zen_auth/errors/user.py
zen_auth/logger/__init__.py
zen_auth/logger/formatter.py
zen_auth/logger/logger.py
zenauth-0.1.2.dist-info/licenses/LICENSE
zenauth-0.1.2.dist-info/METADATA
zenauth-0.1.2.dist-info/WHEEL
zenauth-0.1.2.dist-info/top_level.txt
zenauth-0.1.2.dist-info/RECORD
